HISTORY.rst
LICENSE
README.rst
hierarchical_placement.png
initial_placement.png
setup.py
.github/ISSUE_TEMPLATE/bug_report.md
hierplace/HierPlace.py
hierplace/__init__.py
hierplace.egg-info/PKG-INFO
hierplace.egg-info/SOURCES.txt
hierplace.egg-info/dependency_links.txt
hierplace.egg-info/not-zip-safe
hierplace.egg-info/top_level.txt
tests/CAT.kicad_pcb
tests/CAT.net