Metadata-Version: 2.1
Name: hierplace
Version: 1.0.0
Summary: Groups and arranges KiCAD PCBNEW board parts so they reflect the design hierarchy.
Home-page: https://github.com/devbisme/HierPlace
Author: Dave Vandenbout
Author-email: devb@xess.com
License: MIT license
Project-URL: Documentation, https://github.com/devbisme/HierPlace/blob/master/README.rst
Project-URL: Source, https://github.com/devbisme/HierPlace
Project-URL: Changelog, https://github.com/devbisme/HierPlace/blob/master/HISTORY.rst
Project-URL: Tracker, https://github.com/devbisme/HierPlace/issues
Keywords: HierPlace KiCad EDA PCBNEW
Platform: UNKNOWN
Classifier: Development Status :: 5 - Production/Stable
Classifier: Intended Audience :: Manufacturing
Classifier: License :: OSI Approved :: MIT License
Classifier: Natural Language :: English
Classifier: Operating System :: OS Independent
Classifier: Programming Language :: Python :: 2.7
Classifier: Programming Language :: Python :: 3
Classifier: Topic :: Scientific/Engineering :: Electronic Design Automation (EDA)
License-File: LICENSE
